[
  {
    "id": "task_finish",
    "name": "SM - Task - Finish",
    "nodes": [
      {
        "parameters": {},
        "id": "trigger",
        "name": "When Executed by Another Workflow",
        "type": "n8n-nodes-base.executeWorkflowTrigger",
        "typeVersion": 1,
        "position": [0, 0]
      },
      {
        "parameters": {
          "jsCode": "const RUBLE_EXCHANGE_RATE = 79;\nconst billing_polza = Number($json.billing_polza) - Number($json.amount);\nconst billing_neuro = -(Number($json.billing_neuro) - Number($json.total_usage)) / 100;\nconst diff = DateTime.fromISO($json.created_at).diff(DateTime.fromISO($json.finished_at)).negate().toFormat(\"hh':'mm':'ss\");\nconst avv_time = DateTime.fromISO($json.created_at).diff(DateTime.fromISO($json.finished_at)).negate().toMillis() / (Number($json.chunks_total) || 1) / 1000;\nconst avv_cost = (billing_polza + billing_neuro * RUBLE_EXCHANGE_RATE) / (Number($json.chunks_total) || 1);\n\nreturn {\n  message: `\\n✅ <b>Перевод завершен!</b>\\n\\n📄 Документ (исходный): ${$json.file_name}\\n📄 Документ (с переводом): ${$json.translated_file}\\n\\n💰 Итоговая стоимость Polza.ai: ₽${billing_polza.toFixed(2)}\\n💰 Итоговая стоимость NeuroAPI: $${billing_neuro.toFixed(2)} (₽${(billing_neuro * RUBLE_EXCHANGE_RATE).toFixed(2).toString().replace(/\\B(?=(\\d{3})+(?!\\d))/g, \" \")})\\n\\n🗓 Старт: <code>${DateTime.fromISO($json.created_at).toFormat(\"dd.MM.yyyy HH:mm:ss\")}</code>\\n⏱ Переведено за: <code>${diff} (чч:мм:сс)</code>\\n\\n🔢 <b>Чанков переведено: ${$json.chunks_total}</b>\\n⌛ Среднее время перевода 1 чанка: ${(avv_time).toLocaleString()} сек.\\n💰 Средняя стоимость 1 чанка ≈ ₽${avv_cost.toFixed(2)}\\n\\n<i>Сообщение сгенерировано автоматически.</i>`,\n  type: 'finish',\n  button: {}\n};"
        },
        "id": "code",
        "name": "Format",
        "type": "n8n-nodes-base.code",
        "typeVersion": 2,
        "position": [220, 0]
      }
    ],
    "connections": {
      "When Executed by Another Workflow": {
        "main": [[{ "node": "Format", "type": "main", "index": 0 }]]
      }
    },
    "active": true,
    "settings": {
      "executionOrder": "v1"
    }
  }
]
